rconfig/__init__.py
rconfig/utils/__init__.py
rconfig/utils/more_yaml.py
rconfig-2.1.dist-info/LICENSE
rconfig-2.1.dist-info/METADATA
rconfig-2.1.dist-info/WHEEL
rconfig-2.1.dist-info/top_level.txt
rconfig-2.1.dist-info/RECORD
