Metadata-Version: 2.1
Name: rconfig
Version: 2.1
Summary: Python config
Home-page: UNKNOWN
Author: rivergold
Author-email: jinghe.rivergold@gmail.com
License: MIT
Platform: UNKNOWN
License-File: LICENSE
Requires-Dist: addict
Requires-Dist: pyyaml
